project1/rtl/complex_gate.vhd
library ieee;
use ieee.std_logic_1164.all;

entity complex_gate is
    port (
        a : in  std_logic;
        b : in  std_logic;
        c : in  std_logic;
        y : out std_logic
    );
end entity complex_gate;

architecture rtl of complex_gate is
begin
    y <= (a and b) or (not c);
end architecture rtl;

project1/tb/complex_gate_tb.vhd
library ieee;
use ieee.std_logic_1164.all;

entity complex_gate_tb is
end entity complex_gate_tb;

architecture sim of complex_gate_tb is
    signal a : std_logic := '0';
    signal b : std_logic := '0';
    signal c : std_logic := '0';
    signal y : std_logic;
begin

    dut : entity work.complex_gate
        port map (
            a => a,
            b => b,
            c => c,
            y => y
        );

    stimulus : process
    begin

        a <= '0';
        b <= '0';
        c <= '0';
        wait for 10 ns;
        assert (y = '1') report "Test failed for a=0, b=0, c=0" severity error;

        a <= '0';
        b <= '1';
        c <= '0';
        wait for 10 ns;
        assert (y = '1') report "Test failed for a=0, b=1, c=0" severity error;

        a <= '1';
        b <= '0';
        c <= '0';
        wait for 10 ns;
        assert (y = '1') report "Test failed for a=1, b=0, c=0" severity error;

        a <= '1';
        b <= '1';
        c <= '0';
        wait for 10 ns;
        assert (y = '1') report "Test failed for a=1, b=1, c=0" severity error;

        a <= '0';
        b <= '0';
        c <= '1';
        wait for 10 ns;
        assert (y = '0') report "Test failed for a=0, b=0, c=1" severity error;

        a <= '0';
        b <= '1';
        c <= '1';
        wait for 10 ns;
        assert (y = '0') report "Test failed for a=0, b=1, c=1" severity error;

        a <= '1';
        b <= '0';
        c <= '1';
        wait for 10 ns;
        assert (y = '0') report "Test failed for a=1, b=0, c=1" severity error;

        a <= '1';
        b <= '1';
        c <= '1';
        wait for 10 ns;
        assert (y = '1') report "Test failed for a=1, b=1, c=1" severity error;

        wait;
    end process;

end architecture sim;

project1/sim/complex_gate.vcd
$date
  Fri Sep 11 19:50:28 2026
$end
$version
  GHDL v0
$end
$timescale
  1 fs
$end
$scope module standard $end
$upscope $end
$scope module textio $end
$upscope $end
$scope module std_logic_1164 $end
$upscope $end
$scope module complex_gate_tb $end
$var reg 1 ! a $end
$var reg 1 " b $end
$var reg 1 # c $end
$var reg 1 $ y $end
$scope module dut $end
$var reg 1 % a $end
$var reg 1 & b $end
$var reg 1 ' c $end
$var reg 1 ( y $end
$upscope $end
$upscope $end
$enddefinitions $end
#0
0!
0"
0#
1$
0%
0&
0'
1(
#10000000
1"
1&
#20000000
1!
0"
1%
0&
#30000000
1"
1&
#40000000
0!
0"
1#
0$
0%
0&
1'
0(
#50000000
1"
1&
#60000000
1!
0"
1%
0&
#70000000
1"
1$
1&
1(
