project1/rtl/counter4.vhd
library ieee;

use ieee.std_logic_1164.all;
use ieee.numeric_std.all;

entity counter4 is
    port (
        clk   : in  std_logic;
        reset : in  std_logic;
        enable : in std_logic;
        count : out unsigned(3 downto 0)
    );
end entity counter4;

architecture rtl of counter4 is
    signal count_reg : unsigned(3 downto 0);
begin
    process(clk)
    begin
        if rising_edge(clk) then
            if reset = '1' then
                count_reg <= (others => '0'); -- set all values to zero
            elsif enable = '1' then
                count_reg <= count_reg + 1;
            end if;
        end if;
    end process;
    count <= count_reg;
end architecture rtl;

project1/tb/counter4_tb.vhd
library ieee;

use ieee.std_logic_1164.all;
use ieee.numeric_std.all;
use std.env.all;

entity counter4_tb is
end entity counter4_tb;

architecture sim of counter4_tb is
    signal clk    : std_logic := '0';
    signal reset  : std_logic := '0';
    signal enable : std_logic := '0';
    signal count  : unsigned(3 downto 0);
begin
    dut: entity work.counter4
        port map (
            clk    => clk,
            reset  => reset,
            enable => enable,
            count  => count
        );

    clock_process : process
    begin
        clk <= '0';
        wait for 5 ns;
        clk <= '1';
        wait for 5 ns;
    end process;

    stimulus: process
    begin
        
        reset <= '1';
        wait until rising_edge(clk); wait for 1 ns;
        reset <= '0';
        assert (count = "0000") report "Test failed for reset" severity error;

        wait until rising_edge(clk); wait for 1 ns;
        assert (count = "0000") report "Test failed for not enabled" severity error;

        enable <= '1';
        wait until rising_edge(clk); wait for 1 ns;
        assert (count = "0001") report "Test failed for count 1" severity error;

        wait until rising_edge(clk); wait for 1 ns;
        assert (count = "0010") report "Test failed for count 2" severity error;

        wait until rising_edge(clk); wait for 1 ns;
        assert (count = "0011") report "Test failed for count 3" severity error;

        wait until rising_edge(clk); wait for 1 ns;
        assert (count = "0100") report "Test failed for count 4" severity error;

        for i in 5 to 15 loop
            wait until rising_edge(clk); wait for 1 ns;
            assert (count = to_unsigned(i, 4)) report "Test failed for count " & integer'image(i) severity error;
        end loop;

        assert (count = "1111") report "Test failed for count 15" severity error;

        wait until rising_edge(clk); wait for 1 ns; -- 0000
        assert (count = "0000") report "Test failed for count wrap around" severity error;

        wait until rising_edge(clk); wait for 1 ns; -- 0001
        enable <= '0';
        wait until rising_edge(clk); wait for 1 ns; -- 0001
        assert (count = "0001") report "Test failed for count 1 w/o enable" severity error;
        
        std.env.stop;
    end process;
end architecture sim;

project1/sim/counter4.vcd
$date
  Wed Sep 16 13:46:41 2026
$end
$version
  GHDL v0
$end
$timescale
  1 fs
$end
$scope module standard $end
$upscope $end
$scope module textio $end
$upscope $end
$scope module std_logic_1164 $end
$upscope $end
$scope module numeric_std $end
$upscope $end
$scope module env $end
$upscope $end
$scope module counter4_tb $end
$var reg 1 ! clk $end
$var reg 1 " reset $end
$var reg 1 # enable $end
$var reg 4 $ count[3:0] $end
$scope module dut $end
$var reg 1 % clk $end
$var reg 1 & reset $end
$var reg 1 ' enable $end
$var reg 4 ( count[3:0] $end
$var reg 4 ) count_reg[3:0] $end
$upscope $end
$upscope $end
$enddefinitions $end
#0
0!
1"
0#
bUUUU $
0%
1&
0'
bUUUU (
bUUUU )
#5000000
1!
b0000 $
1%
b0000 (
b0000 )
#6000000
0"
0&
#10000000
0!
0%
#15000000
1!
1%
#16000000
1#
1'
#20000000
0!
0%
#25000000
1!
b0001 $
1%
b0001 (
b0001 )
#30000000
0!
0%
#35000000
1!
b0010 $
1%
b0010 (
b0010 )
#40000000
0!
0%
#45000000
1!
b0011 $
1%
b0011 (
b0011 )
#50000000
0!
0%
#55000000
1!
b0100 $
1%
b0100 (
b0100 )
#60000000
0!
0%
#65000000
1!
b0101 $
1%
b0101 (
b0101 )
#70000000
0!
0%
#75000000
1!
b0110 $
1%
b0110 (
b0110 )
#80000000
0!
0%
#85000000
1!
b0111 $
1%
b0111 (
b0111 )
#90000000
0!
0%
#95000000
1!
b1000 $
1%
b1000 (
b1000 )
#100000000
0!
0%
#105000000
1!
b1001 $
1%
b1001 (
b1001 )
#110000000
0!
0%
#115000000
1!
b1010 $
1%
b1010 (
b1010 )
#120000000
0!
0%
#125000000
1!
b1011 $
1%
b1011 (
b1011 )
#130000000
0!
0%
#135000000
1!
b1100 $
1%
b1100 (
b1100 )
#140000000
0!
0%
#145000000
1!
b1101 $
1%
b1101 (
b1101 )
#150000000
0!
0%
#155000000
1!
b1110 $
1%
b1110 (
b1110 )
#160000000
0!
0%
#165000000
1!
b1111 $
1%
b1111 (
b1111 )
#170000000
0!
0%
#175000000
1!
b0000 $
1%
b0000 (
b0000 )
#180000000
0!
0%
#185000000
1!
b0001 $
1%
b0001 (
b0001 )
#186000000
0#
0'
